{
  "videos": [
    {
      "title": "Celebrate the Music - Der Film",
      "videoId": "D649Q4QQsME"
    },
    {
      "title": "\"Celebrate the music\" // 11.09.2022 \"Sportiv - Inklusiv - Aktiv dabei sein\"",
      "videoId": "mJsl1Hwu7B0"
    },
    {
      "title": "\"Celebrate the music\" // 12.05.2022 Nelson Mandela Schule",
      "videoId": "x8POp5okdqk"
    },
    {
      "title": "\"Celebrate the music\" // 06.05.22 Grundschule Bindfeldweg",
      "videoId": "yaepk0pOa8c"
    },
    {
      "title": "\"Celebrate the music\" // 05.05.22 ReBBZ",
      "videoId": "iKk9QSiuOF4"
    }
  ],
  "title": "celebrate-the-music"
}
